gimbench/__init__.py
gimbench/arguments.py
gimbench/base.py
gimbench/cv/__init__.py
gimbench/cv/cv_parse.py
gimbench/cv/evaluators.py
gimbench/cv/schema.py
gimbench/log.py
gimbench/match/__init__.py
gimbench/match/evaluators.py
gimbench/match/gim_regex.py
gimbench/mcqa/__init__.py
gimbench/mcqa/evaluators.py
gimbench/mcqa/gpqa_diamond.py
gimbench/mcqa/medmcqa.py
gimbench/mcqa/mmlu_pro.py
gimbench/mcqa/qasc.py
gimbench/models.py
gimbench/ppl/__init__.py
gimbench/ppl/evaluators.py
gimbench/ppl/gim_sft.py
gimbench/tools/aggregate_results.py
gimbench-0.2.7.dist-info/WHEEL
gimbench-0.2.7.dist-info/METADATA
gimbench-0.2.7.dist-info/RECORD
