Metadata-Version: 2.3
Name: gimbench
Version: 0.2.7
Summary: Benchmarking the guided infilling models.
Requires-Dist: datasets>=4.4.1
Requires-Dist: gimkit>=0.1.1
Requires-Dist: rich>=14.2.0
Requires-Dist: vllm>=0.14.0
Requires-Python: >=3.10
